{
  "version": "0.3.14-fixed",
  "steps": [
    {
      "tag": "CreateModel",
      "model": "Sessions"
    },
    {
      "tag": "CreateField",
      "model": "Sessions",
      "field": "id",
      "type": "Int",
      "arity": "Required"
    },
    {
      "tag": "CreateDirective",
      "location": {
        "path": {
          "tag": "Field",
          "model": "Sessions",
          "field": "id"
        },
        "directive": "default"
      }
    },
    {
      "tag": "CreateArgument",
      "location": {
        "tag": "Directive",
        "path": {
          "tag": "Field",
          "model": "Sessions",
          "field": "id"
        },
        "directive": "default"
      },
      "argument": "",
      "value": "autoincrement()"
    },
    {
      "tag": "CreateDirective",
      "location": {
        "path": {
          "tag": "Field",
          "model": "Sessions",
          "field": "id"
        },
        "directive": "id"
      }
    },
    {
      "tag": "CreateField",
      "model": "Sessions",
      "field": "ChatID",
      "type": "Int",
      "arity": "Required"
    },
    {
      "tag": "CreateDirective",
      "location": {
        "path": {
          "tag": "Field",
          "model": "Sessions",
          "field": "ChatID"
        },
        "directive": "unique"
      }
    },
    {
      "tag": "CreateField",
      "model": "Sessions",
      "field": "spentCities",
      "type": "Json",
      "arity": "Optional"
    },
    {
      "tag": "CreateField",
      "model": "Sessions",
      "field": "lastLetter",
      "type": "String",
      "arity": "Optional"
    },
    {
      "tag": "CreateField",
      "model": "Sessions",
      "field": "scoreInSession",
      "type": "Int",
      "arity": "Optional"
    },
    {
      "tag": "CreateField",
      "model": "botContext",
      "field": "sessions",
      "type": "Sessions",
      "arity": "Required"
    }
  ]
}